weave_cli-1.1.0.dist-info/licenses/LICENSE
wnc/__init__.py
wnc/__main__.py
wnc/api.py
wnc/cli.py
wnc/wizard.py
wnc/analyzers/__init__.py
wnc/analyzers/risk.py
wnc/scanners/__init__.py
wnc/scanners/arp.py
wnc/scanners/banners.py
wnc/scanners/cameras.py
wnc/scanners/fingerprints.py
wnc/scanners/geo.py
wnc/scanners/lan.py
wnc/scanners/mdns.py
wnc/scanners/network.py
wnc/scanners/onvif.py
wnc/scanners/onvif_client.py
wnc/scanners/ports.py
wnc/scanners/speed.py
wnc/scanners/ssdp.py
wnc/scanners/udp.py
wnc/scanners/wifi.py
weave_cli-1.1.0.dist-info/METADATA
weave_cli-1.1.0.dist-info/WHEEL
weave_cli-1.1.0.dist-info/entry_points.txt
weave_cli-1.1.0.dist-info/top_level.txt
weave_cli-1.1.0.dist-info/RECORD
