Metadata-Version: 2.4
Name: weave-cli
Version: 1.1.0
Summary: Weave Network CLI: network discovery, async port scanning, camera detection, and risk analysis.
Author: Kai Gartner
License: PolyForm Noncommercial License 1.0.0
Project-URL: Homepage, https://github.com/ThePhotoCodeGrapher/Network-CLI-scanner
Project-URL: Issues, https://github.com/ThePhotoCodeGrapher/Network-CLI-scanner/issues
Keywords: network,scanner,security,cli,camera,onvif,discovery,port-scan,iot
Classifier: Programming Language :: Python :: 3
Classifier: Programming Language :: Python :: 3 :: Only
Classifier: Programming Language :: Python :: 3.9
Classifier: Programming Language :: Python :: 3.10
Classifier: Programming Language :: Python :: 3.11
Classifier: Environment :: Console
Classifier: Intended Audience :: Information Technology
Classifier: Intended Audience :: System Administrators
Classifier: Topic :: Security
Classifier: Topic :: System :: Networking
Classifier: License :: Other/Proprietary License
Requires-Python: >=3.9
License-File: LICENSE
Requires-Dist: typer[all]==0.12.3
Requires-Dist: rich==13.7.1
Requires-Dist: psutil==5.9.8
Requires-Dist: async-timeout==4.0.3
Requires-Dist: httpx==0.27.2
Requires-Dist: netaddr==1.3.0
Requires-Dist: speedtest-cli==2.1.3
Requires-Dist: lxml==5.3.0
Requires-Dist: zeep==4.3.1
Requires-Dist: requests==2.32.3
Requires-Dist: certifi==2024.7.4
Dynamic: license-file
